nippy/__init__.py
nippy/bugger.py
nippy/callable_arguments_peek.py
nippy/class_analysis.py
nippy/compute.py
nippy/context_managers.py
nippy/copy_of_data_flow.py
nippy/counter.py
nippy/data_flow.py
nippy/data_source.py
nippy/decorators.py
nippy/descriptors.py
nippy/geo.py
nippy/importing.py
nippy/ipython.py
nippy/log.py
nippy/my_proj_populate.py
nippy/num.py
nippy/pfilt.py
nippy/pfunc.py
nippy/pickling.py
nippy/pobj.py
nippy/prand.py
nippy/pstore.py
nippy/resources.py
nippy/slurping.py
nippy/time.py
nippy/timer.py
nippy/udate.py
nippy/uiter.py
nippy/ujson.py
nippy/ulist.py
nippy/utime.py
nippy/var.py
nippy/code/__init__.py
nippy/howto/__init__.py
nippy/howto/refer_to_relative_path.py
nippy/imports/__init__.py
nippy/imports/code.py
nippy/imports/data_analysis.py
nippy/imports/ipython_main_imports.py
nippy/imports/ipython_utils.py
nippy/imports/jan14.py
nippy/imports/modelling.py
nippy/imports/plotting_utils.py
nippy/imports/scraping_imports.py
nippy/imports/text_processing.py
nippy/tests/__init__.py
nippy/tests/uiter.py
nippy-0.0.3.dist-info/LICENSE
nippy-0.0.3.dist-info/METADATA
nippy-0.0.3.dist-info/WHEEL
nippy-0.0.3.dist-info/top_level.txt
nippy-0.0.3.dist-info/RECORD
