Metadata-Version: 2.1
Name: nippy
Version: 0.0.3
Summary: Miscellenous utils
Home-page: https://github.com/thorwhalen/newut/tree/master/nippy
Author: Thor Whalen
License: mit
Platform: any
License-File: LICENSE
